Metadata-Version: 2.1
Name: assetnote-cli
Version: 0.0.1
Summary: CLI for interacting with Assetnote's Continuous Security Platform GraphQL API
Home-page: https://github.com/assetnote/assetnote_cli
Author: shubham_shah
Author-email: sshah@assetnote.io
License: UNKNOWN
Download-URL: https://github.com/assetnote/assetnote_cli/archive/0.0.1.tar.gz
Platform: UNKNOWN
Classifier: Development Status :: 3 - Alpha
Classifier: Intended Audience :: Developers
Classifier: Topic :: Software Development :: Libraries
Classifier: License :: OSI Approved :: GNU Affero General Public License v3
Classifier: Programming Language :: Python :: 3.8
Requires-Python: >=0.0.1
License-File: LICENSE
